deepx_dock/CONSTANT.py
deepx_dock/__init__.py
deepx_dock/_version.py
deepx_dock/misc.py
deepx_dock/_cli/__init__.py
deepx_dock/_cli/registry.py
deepx_dock/analyze/dataset/_cli.py
deepx_dock/analyze/dataset/analyze_dataset.py
deepx_dock/analyze/dataset/dft_features.py
deepx_dock/analyze/dataset/e3nn_irreps.py
deepx_dock/analyze/dft_equiv/_cli.py
deepx_dock/analyze/dft_equiv/gen_struct.py
deepx_dock/analyze/dft_equiv/jd.h5
deepx_dock/analyze/dft_equiv/test_equiv.py
deepx_dock/analyze/error/_cli.py
deepx_dock/analyze/error/with_infer_res.py
deepx_dock/analyze/error/with_train_log.py
deepx_dock/compute/density_matrix/density_matrix.py
deepx_dock/compute/eigen/_cli.py
deepx_dock/compute/eigen/band.py
deepx_dock/compute/eigen/fermi_dos.py
deepx_dock/compute/eigen/hamiltonian.py
deepx_dock/compute/eigen/wavefunction.py
deepx_dock/compute/overlap/_cli.py
deepx_dock/compute/overlap/findpairs.py
deepx_dock/compute/overlap/overlap.py
deepx_dock/compute/pyscf/pyscf_hooker.py
deepx_dock/convert/abacus/_cli.py
deepx_dock/convert/abacus/translate_abacus_to_deeph.py
deepx_dock/convert/deeph/_cli.py
deepx_dock/convert/deeph/minus_core_hamiltonian.py
deepx_dock/convert/deeph/standardize_hamiltonian.py
deepx_dock/convert/deeph/translate_old_dataset_to_new.py
deepx_dock/convert/fhi_aims/_cli.py
deepx_dock/convert/fhi_aims/aims_to_deeph.py
deepx_dock/convert/fhi_aims/parse_ctrl_in.py
deepx_dock/convert/fhi_aims/single_atom_aims_to_deeph.py
deepx_dock/convert/hopcp/_cli.py
deepx_dock/convert/hopcp/establish_petsc_install_dir.py
deepx_dock/convert/hopcp/translate_deeph_to_petsc.py
deepx_dock/convert/hopcp/_template_petsc_install/Makefile
deepx_dock/convert/hopcp/_template_petsc_install/_download.sh
deepx_dock/convert/hopcp/_template_petsc_install/_install.sh
deepx_dock/convert/openmx/_cli.py
deepx_dock/convert/openmx/translate_openmx_to_deeph.py
deepx_dock/convert/pyscf/_cli.py
deepx_dock/convert/qe/_cli.py
deepx_dock/convert/qe/translate_espresso_to_deeph.py
deepx_dock-0.9.9.dist-info/licenses/LICENSE
deepx_dock-0.9.9.dist-info/METADATA
deepx_dock-0.9.9.dist-info/WHEEL
deepx_dock-0.9.9.dist-info/entry_points.txt
deepx_dock-0.9.9.dist-info/top_level.txt
deepx_dock-0.9.9.dist-info/RECORD
