Metadata-Version: 2.4
Name: deepx-dock
Version: 0.9.9
Summary: DeepH-dock seamlessly integrates deep learning with first-principles calculations. It serves as a modular and extensible bridge, functioning both as the dedicated interface for the DeepH-pack suite and as a standalone tool for coupling deep learning models with computational materials science workflows.
Author-email: DeepH team <deeph-pack@outlook.com>
License-Expression: GPL-3.0-or-later
Project-URL: Repository, https://github.com/kYangLi/DeepH-dock.git
Keywords: DeepH-dock,DeepH-pack,Physics,Deep Learning,Graph Neural Network,JAX,FHI-aims,OpenMX,ABACUS,SIESTA,HPRO
Classifier: Development Status :: 5 - Production/Stable
Classifier: Programming Language :: Python :: 3.13
Requires-Python: <3.15,>=3.12
License-File: LICENSE
Requires-Dist: numpy
Requires-Dist: h5py
Requires-Dist: tqdm
Requires-Dist: toml
Requires-Dist: scipy
Requires-Dist: joblib
Requires-Dist: matplotlib
Requires-Dist: mendeleev
Requires-Dist: libtetrabz
Requires-Dist: threadpoolctl
Requires-Dist: click
Requires-Dist: ase
Requires-Dist: mpi4py
Provides-Extra: petsc
Requires-Dist: mpi4py; extra == "petsc"
Requires-Dist: numpy; extra == "petsc"
Requires-Dist: petsc; extra == "petsc"
Requires-Dist: petsc4py; extra == "petsc"
Provides-Extra: pyscf
Requires-Dist: pyscf; extra == "pyscf"
Provides-Extra: fhiaims
Requires-Dist: scalapack4py; extra == "fhiaims"
Requires-Dist: asi4py; extra == "fhiaims"
Provides-Extra: docs
Requires-Dist: sphinx; extra == "docs"
Requires-Dist: sphinx-book-theme; extra == "docs"
Requires-Dist: sphinx-autobuild; extra == "docs"
Requires-Dist: ipykernel; extra == "docs"
Requires-Dist: myst_nb; extra == "docs"
Requires-Dist: nbstripout; extra == "docs"
Requires-Dist: recommonmark; extra == "docs"
Requires-Dist: ipython_genutils; extra == "docs"
Requires-Dist: sphinx-design; extra == "docs"
Requires-Dist: jupytext; extra == "docs"
Requires-Dist: docutils; extra == "docs"
Dynamic: license-file
